vfcode/__init__.py
vfcode/config.py
vfcode/generator.py
vfcode/render.py
vfcode/utils.py
vfcode/fonts/ch/STCAIYUN.TTF
vfcode/fonts/ch/STLITI.TTF
vfcode/fonts/ch/STXINGKA.TTF
vfcode/fonts/en/AdobeGothicStd-Bold.otf
vfcode/fonts/en/AxureHandwriting-Bold.otf
vfcode/fonts/en/COOPBL.TTF
vfcode/fonts/en/ITCKRIST.TTF
vfcode/fonts/en/LHANDW.TTF
vfcode-0.0.2.dist-info/DESCRIPTION.rst
vfcode-0.0.2.dist-info/METADATA
vfcode-0.0.2.dist-info/RECORD
vfcode-0.0.2.dist-info/WHEEL
vfcode-0.0.2.dist-info/metadata.json
vfcode-0.0.2.dist-info/top_level.txt
vfcode-0.0.2.dist-info/zip-safe
