Metadata-Version: 2.0
Name: vfcode
Version: 0.0.2
Summary: 验证码生成库.
Home-page: https://github.com/xin053/vfcode
Author: xin053
Author-email: 13207130066.cool@163.com
License: Apache License 2
Keywords: 验证码
Platform: UNKNOWN
Classifier: License :: OSI Approved :: Apache Software License
Classifier: Programming Language :: Python
Classifier: Intended Audience :: Developers
Classifier: Operating System :: OS Independent
